damtsavi_core/__init__.py
damtsavi_core/actions/__init__.py
damtsavi_core/patterns/__init__.py
damtsavi_core-0.0.data/scripts/damtsavi
damtsavi_core-0.0.dist-info/DESCRIPTION.rst
damtsavi_core-0.0.dist-info/METADATA
damtsavi_core-0.0.dist-info/RECORD
damtsavi_core-0.0.dist-info/WHEEL
damtsavi_core-0.0.dist-info/metadata.json
damtsavi_core-0.0.dist-info/top_level.txt
